ssb_gcp_identity_client/__init__.py
ssb_gcp_identity_client/__main__.py
ssb_gcp_identity_client/clients.py
ssb_gcp_identity_client/credentials.py
ssb_gcp_identity_client/py.typed
ssb_gcp_identity_client-0.2.1.dist-info/METADATA
ssb_gcp_identity_client-0.2.1.dist-info/WHEEL
ssb_gcp_identity_client-0.2.1.dist-info/entry_points.txt
ssb_gcp_identity_client-0.2.1.dist-info/licenses/LICENSE
ssb_gcp_identity_client-0.2.1.dist-info/RECORD
