Metadata-Version: 2.4
Name: ssb-gcp-identity-client
Version: 0.2.1
Summary: SSB GCP Identity Client
License-Expression: MIT
License-File: LICENSE
Author: Joachim Holst
Author-email: oho@ssb.no
Maintainer: Statistics Norway, Data collection platform Department (722)
Requires-Python: >=3.10,<4.0
Classifier: Development Status :: 3 - Alpha
Classifier: Programming Language :: Python :: 3
Classifier: Programming Language :: Python :: 3.10
Classifier: Programming Language :: Python :: 3.11
Classifier: Programming Language :: Python :: 3.12
Classifier: Programming Language :: Python :: 3.13
Classifier: Programming Language :: Python :: 3.14
Requires-Dist: click (>=8.0.1)
Requires-Dist: google-auth (>=2.25.0)
Requires-Dist: google-cloud-storage (>=2.10.0)
Project-URL: Changelog, https://github.com/statisticsnorway/ssb-gcp-identity-client/releases
Project-URL: Documentation, https://statisticsnorway.github.io/ssb-gcp-identity-client
Project-URL: Homepage, https://github.com/statisticsnorway/ssb-gcp-identity-client
Project-URL: Repository, https://github.com/statisticsnorway/ssb-gcp-identity-client
